taot/__init__.py
taot/agent.py
taot/message.py
taot/models.py
taot-0.2.4.dist-info/licenses/LICENSE.txt
taot-0.2.4.dist-info/METADATA
taot-0.2.4.dist-info/WHEEL
taot-0.2.4.dist-info/top_level.txt
taot-0.2.4.dist-info/RECORD
