Metadata-Version: 2.4
Name: taot
Version: 0.2.4
Summary: Tool Ahead of Time (TAoT)
Home-page: https://github.com/leockl/tool-ahead-of-time
Author: Leo Chow
Author-email: Leo Chow <leo.chow11@gmail.com>
Project-URL: Homepage, https://github.com/leockl/tool-ahead-of-time
Project-URL: Bug Tracker, https://github.com/leockl/tool-ahead-of-time/issues
Classifier: Programming Language :: Python :: 3
Classifier: License :: OSI Approved :: MIT License
Classifier: Operating System :: OS Independent
Requires-Python: >=3.8
License-File: LICENSE.txt
Dynamic: author
Dynamic: home-page
Dynamic: license-file
Dynamic: requires-python
